tianrannlp/__init__.py
tianrannlp/preprocess/__init__.py
tianrannlp/preprocess/stringPreprocessUtils.py
tianrannlp/rules/__init__.py
tianrannlp/rules/stringCheckUtils.py
tianrannlp-0.0.4.dist-info/METADATA
tianrannlp-0.0.4.dist-info/WHEEL
tianrannlp-0.0.4.dist-info/top_level.txt
tianrannlp-0.0.4.dist-info/RECORD
