Metadata-Version: 2.1
Name: tianrannlp
Version: 0.0.4
Summary: 文本处理
Home-page: https://github.com/lianyongxing/
Author: tianran
Author-email: 512796933@qq.com
